PyOfficeRobot/__init__.py
PyOfficeRobot/api/__init__.py
PyOfficeRobot/api/chat.py
PyOfficeRobot/api/file.py
PyOfficeRobot/api/friend.py
PyOfficeRobot/api/group.py
PyOfficeRobot/core/WeChatType.py
PyOfficeRobot/core/__init__.py
PyOfficeRobot/core/group/Start.py
PyOfficeRobot/core/group/__init__.py
PyOfficeRobot/core/group/ui_file_py.py
PyOfficeRobot/lib/CONST.py
PyOfficeRobot/lib/__init__.py
PyOfficeRobot/lib/dec/__init__.py
PyOfficeRobot/lib/dec/act_dec.py
PyOfficeRobot/lib/decorator_utils/__init__.py
PyOfficeRobot/lib/decorator_utils/instruction_url.py
pyofficerobot-0.1.26.dist-info/licenses/LICENSE
tests/__init__.py
pyofficerobot-0.1.26.dist-info/METADATA
pyofficerobot-0.1.26.dist-info/WHEEL
pyofficerobot-0.1.26.dist-info/top_level.txt
pyofficerobot-0.1.26.dist-info/RECORD
