Metadata-Version: 2.4
Name: PyOfficeRobot
Version: 0.1.26
Summary: pip install PyOfficeRobot
Home-page: https://www.python-office.com/office/robot.html
Author: CoderWanFeng
Author-email: 1957875073@qq.com
License: MIT
Project-URL: Bug Tracker, https://github.com/CoderWanFeng/PyOfficeRobot/issues
Project-URL: Documentation, https://github.com/CoderWanFeng/PyOfficeRobot/blob/main/README.md
Project-URL: Source Code, https://github.com/CoderWanFeng/PyOfficeRobot
Platform: any
Requires-Python: >=3.6
License-File: LICENSE
Requires-Dist: uiautomation; platform_system == "Windows"
Requires-Dist: pywin32; platform_system == "Windows"
Requires-Dist: pywinauto; platform_system == "Windows"
Requires-Dist: schedule
Requires-Dist: pandas
Requires-Dist: poai
Requires-Dist: xlwt
Requires-Dist: xlrd==1.2.0
Requires-Dist: PySide6
Requires-Dist: porobot
Requires-Dist: loguru
Requires-Dist: pofile
Dynamic: license-file
